py_adaptivecards_templating/__init__.py
py_adaptivecards_templating/template_engine.py
py_adaptivecards_templating-0.1.1.dist-info/licenses/LICENSE
py_adaptivecards_templating-0.1.1.dist-info/METADATA
py_adaptivecards_templating-0.1.1.dist-info/WHEEL
py_adaptivecards_templating-0.1.1.dist-info/top_level.txt
py_adaptivecards_templating-0.1.1.dist-info/RECORD
