Metadata-Version: 2.4
Name: py_adaptivecards_templating
Version: 0.1.1
Summary: This library largely implements the JSON-to-JSON Adaptive Cards Template language for Python. Most features are supported, except for the Adaptive expressions prebuilt functions.
Author-email: Dion Olsthoorn <dion.olsthoorn@gmail.com>
License: MIT License
Project-URL: Homepage, https://github.com/dionoid/py-adaptivecards-templating
Project-URL: Source, https://github.com/dionoid/py-adaptivecards-templating
Project-URL: Issues, https://github.com/dionoid/py-adaptivecards-templating/issues
Requires-Python: >=3.7
License-File: LICENSE
Provides-Extra: test
Requires-Dist: pytest; extra == "test"
Dynamic: license-file
